AUTHORS.rst
CONTRIBUTING.rst
HISTORY.rst
LICENSE
MANIFEST.in
README.rst
setup.cfg
setup.py
docs/Makefile
docs/authors.rst
docs/conf.py
docs/contributing.rst
docs/history.rst
docs/index.rst
docs/installation.rst
docs/make.bat
docs/readme.rst
docs/usage.rst
examples/__init__.py
examples/action_handle.py
examples/local_action_handle.py
examples/send_text_example.py
examples/send_text_example_actions.py
examples/send_text_example_prompt.py
examples/send_user_entities_example.py
tests/__init__.py
tests/test_yige.py
yige/__init__.py
yige/yige.py
yige/yige_action.py
yige/yige_requests.py
yige/yige_user_entities.py
yige.egg-info/PKG-INFO
yige.egg-info/SOURCES.txt
yige.egg-info/dependency_links.txt
yige.egg-info/entry_points.txt
yige.egg-info/not-zip-safe
yige.egg-info/requires.txt
yige.egg-info/top_level.txt