Metadata-Version: 1.1
Name: yige
Version: 0.2.1
Summary: Python library for yige.ai
Home-page: https://github.com/wwj718/yige
Author: wenjiewu
Author-email: wuwenjie718@gmail.com
License: MIT license
Keywords: yige
Platform: UNKNOWN
Classifier: Development Status :: 2 - Pre-Alpha
Classifier: Intended Audience :: Developers
Classifier: License :: OSI Approved :: MIT License
Classifier: Natural Language :: English
Classifier: Programming Language :: Python :: 2
Classifier: Programming Language :: Python :: 2.6
Classifier: Programming Language :: Python :: 2.7
Classifier: Programming Language :: Python :: 3
Classifier: Programming Language :: Python :: 3.3
Classifier: Programming Language :: Python :: 3.4
Classifier: Programming Language :: Python :: 3.5
